simple_framework/__init__.py
simple_framework/simple_framework.py
4i_framework-0.1.4.dist-info/METADATA
4i_framework-0.1.4.dist-info/WHEEL
4i_framework-0.1.4.dist-info/top_level.txt
4i_framework-0.1.4.dist-info/RECORD
